<robot>
  <meta>
    <name>1207.be</name>
<country>BE</country>
<revision>2</revision>
<minversion>4</minversion>
<description>Number lookup for Belgian numbers</description>
<link>https://www.1207.be</link>
<icon>http://phonehook.omnight.com/logos/be_1207.jpg</icon>
</meta>
  
  <set id="root" name="results" tags="lookup">
    <set id="08339664575178176" name="#load" url="http://www.1207.be/">
      <set id="024102708557620645" name="formid" paramoutput="true" value="/&lt;input[^&gt;]*name=&quot;form_build_id&quot;[^&gt;]*value=&quot;(.*?)&quot;/" />
      <set id="019256239337846637" name="#lookup" url="http://www.1207.be/" postrequest="true" postdata="keyword=${telnr}&amp;city=&amp;op=Zoeken&amp;form_build_id=${formid}&amp;form_id=feedback_form" requestfields="Header" requestvalue="Content-Type:application/x-www-form-urlencoded">
        <set id="06861412695143372" name="#result" value="/&lt;div[^&gt;]*class=&quot;[^&quot;]*card(.*?)(?=&lt;div[^&gt;]*class=&quot;[^&quot;]*card|&lt;div[^&gt;]*class=&quot;[^&quot;]*tool)/">
          <set id="09308745434973389" name="field" value="/&lt;h1 class=&quot;fn org&quot;&gt;\s*&lt;a[^&gt;]*&gt;\s*(.*?)\s*&lt;/a&gt;/">
            <set id="06383206094615161" name="title" value="Name" />
            <set id="09072138429619372" name="value" value="/(.+)/" />
            <set id="09177366148214787" name="stitle" value="name" />
          </set>
          <set id="019541398342698812" name="field" value="/&lt;div class=&quot;value adr&quot;&gt;(.*?)&lt;/div&gt;/">
            <set id="038466155622154474" name="title" value="Address" />
            <set id="04521711841225624" name="value" value="/&lt;[^&gt;]*&gt;/" decode="RegexReplace" />
            <set id="08430362849030644" name="stitle" value="address" />
          </set>
        </set>
      </set>
    </set>
  </set>
</robot>